{
    "meta": {
        "ailment": {
            "name": "none",
            "url": "https://pokeapi.co/api/v2/move-ailment/0/"
        },
        "ailment_chance": 0,
        "category": {
            "name": "unique",
            "url": "https://pokeapi.co/api/v2/move-category/13/"
        },
        "crit_rate": 0,
        "drain": 0,
        "flinch_chance": 0,
        "healing": 0,
        "max_hits": null,
        "max_turns": null,
        "min_hits": null,
        "min_turns": null,
        "stat_chance": 0
    },
    "power": null,
    "accuracy": 100,
    "pp": 5,
    "description": "\u3042\u3044\u3066\u3092\u3000\u306b\u3052\u3089\u308c\u306a\u304f\u3059\u308b\u3002\n\u304b\u305f\u3081\u3089\u308c\u305f\u3000\u3042\u3044\u3066\u306f\u3000\u307e\u3044\u30bf\u30fc\u30f3\n\u307c\u3046\u304e\u3087\u3068\u3000\u3068\u304f\u307c\u3046\u304c\u3000\u3055\u304c\u308b\u3002",
    "damage_class": "status",
    "type": "fighting",
    "effect_chance": null,
    "effect_names": [],
    "retreat": 1.0,
    "stat_changes": {
        "self": {},
        "target": {}
    }
}